README.md
setup.py
bin/spesh
spesh/version.py
spesh.egg-info/PKG-INFO
spesh.egg-info/SOURCES.txt
spesh.egg-info/dependency_links.txt
spesh.egg-info/requires.txt
spesh.egg-info/top_level.txt