Metadata-Version: 2.1
Name: spesh
Version: 0.0.1
Summary: SPEctra SHow. A tool for gamma and other spectra, uses ROOT, also for online histograms served via HTTP on port 9009
Author: jaro
Author-email: jaromrax@gmail.com
License: GPL2
